pyFireEye/__init__.py
pyFireEye/ax/__init__.py
pyFireEye/ax/ax_core.py
pyFireEye/cms/__init__.py
pyFireEye/cms/cms_core.py
pyFireEye/faas/__init__.py
pyFireEye/faas/faas_core.py
pyFireEye/hx/__init__.py
pyFireEye/hx/hx_core.py
pyFireEye/utilities/__init__.py
pyFireEye/utilities/exceptions.py
pyFireEye/utilities/params_helper.py
pyFireEye/utilities/responses.py
pyFireEye/utilities/utility.py
pyFireEye/utilities/wrappers.py
pyFireEye-1.0.dist-info/LICENSE
pyFireEye-1.0.dist-info/METADATA
pyFireEye-1.0.dist-info/WHEEL
pyFireEye-1.0.dist-info/top_level.txt
pyFireEye-1.0.dist-info/RECORD
